Workbook

Sheet Исходные данные
A1: Сценарий | B1: Параметр | C1: Техническое имя CSV | D1: Значение | E1: Единица измерения | F1: Описание
A2: Базовый | B2: Календарное время | C2: Calendar_Hours | D2: 720 | E2: ч | F2: Общее календарное время расчётного периода
A3: Базовый | B3: Плановое время работы | C3: Planned_Hours | D3: 480 | E3: ч | F3: Запланированное время работы оборудования
A4: Базовый | B4: Фактическое время работы | C4: Actual_Hours | D4: 390 | E4: ч | F4: Фактическое время работы оборудования
A5: Базовый | B5: Плановый выпуск | C5: Target_Output | D5: 120 | E5: л | F5: Плановый объём выпуска
A6: Базовый | B6: Фактический выпуск | C6: Actual_Output | D6: 95 | E6: л | F6: Фактически обработанный объём
A7: Базовый | B7: Годный объём первого прохода | C7: First_Pass_Good_Units | D7: 71.25 | E7: л | F7: Объём, прошедший контроль с первого раза
A8: Базовый | B8: Итоговый годный объём | C8: Final_Good_Units | D8: 80.75 | E8: л | F8: Итоговый годный объём после переделки
A9: Базовый | B9: Затраты на сырьё | C9: Raw_Material_Cost | D9: 240000 | E9: долл. США | F9: Стоимость использованных сырья и материалов
A10: Базовый | B10: Потребление электроэнергии | C10: Energy_kWh | D10: 115000 | E10: кВт·ч | F10: Потребление электроэнергии за период
A11: Базовый | B11: Тариф на электроэнергию | C11: Energy_Cost_Rate | D11: 0.22 | E11: долл. США/кВт·ч | F11: Стоимость одного киловатт-часа
A12: Базовый | B12: Капитальная стоимость оборудования | C12: Equipment_CAPEX | D12: 28000000 | E12: долл. США | F12: Первоначальная стоимость оборудования
A13: Базовый | B13: Экономический срок амортизации | C13: Amortization_Years_Economic | D13: 3 | E13: лет | F13: Экономический срок службы оборудования
... A37: Стрессовый | B37: Открытость рыночного окна | C37: Market_Window_Open | D37: 1 | E37: 0 или 1 | F37: Признак открытого рыночного окна

Sheet Метрики
A1: Метрика | B1: Пояснение формулы | C1: Используемые параметры | D1: Значение | E1: Единица измерения | F1: Комментарий
A2: Выход годных с первого прохода (FPY) | B2: Годный объём первого прохода / фактический выпуск | C2: Годный объём первого прохода; фактический выпуск | D2: ='Исходные данные'!$D$7/'Исходные данные'!$D$6 -> 0.75 | E2: безразмерная величина | F2: Доля продукции, прошедшей контроль качества без переделки
A3: Итоговый выход годных | B3: Итоговый годный объём / фактический выпуск | C3: Итоговый годный объём; фактический выпуск | D3: ='Исходные данные'!$D$8/'Исходные данные'!$D$6 -> 0.85 | E3: безразмерная величина | F3: Учитывает годную продукцию после переделки
A4: Доступность оборудования | B4: Фактическое время работы / плановое время работы | C4: Фактическое время работы; плановое время работы | D4: ='Исходные данные'!$D$4/'Исходные данные'!$D$3 -> 0.8125 | E4: безразмерная величина | F4: Коэффициент доступности в составе OEE
A5: Производительность оборудования | B5: (Плановое время / плановый выпуск) × фактический выпуск / фактическое время | C5: Плановое время; плановый выпуск; фактический выпуск; фактическое время | D5: =('Исходные данные'!$D$3/'Исходные данные'!$D$5)*'Исходные данные'!$D$6/'Исходные данные'!$D$4 -> 0.97435897 | E5: безразмерная величина | F5: Нормативное время цикла рассчитано в часах на литр
A6: Коэффициент качества | B6: Коэффициент качества = FPY | C6: Выход годных с первого прохода (FPY) | D6: =D2 -> 0.75 | E6: безразмерная величина | F6: Определение коэффициента качества по лекции
A7: Общая эффективность оборудования (OEE) | B7: Доступность × производительность × качество | C7: Доступность; производительность; качество | D7: =D4*D5*D6 -> 0.59375 | E7: безразмерная величина | F7: Операционная эффективность оборудования
A8: Использование календарного времени | B8: Плановое время работы / календарное время | C8: Плановое время работы; календарное время | D8: ='Исходные данные'!$D$3/'Исходные данные'!$D$2 -> 0.66666667 | E8: безразмерная величина | F8: Использование доступного календарного фонда времени
A9: Полная эффективная производительность оборудования (TEEP) | B9: OEE × использование календарного времени | C9: OEE; использование календарного времени | D9: =D7*D8 -> 0.39583333 | E9: безразмерная величина | F9: Показывает использование производственного потенциала CAPEX
A10: Энергетическая ресурсоёмкость | B10: Потребление электроэнергии / итоговый годный объём | C10: Потребление электроэнергии; итоговый годный объём | D10: ='Исходные данные'!$D$10/'Исходные данные'!$D$8 -> 1424.1486 | E10: кВт·ч/л | F10: Потребление энергии на литр итоговой годной продукции
A11: Экономическая ресурсоёмкость | B11: Общие производственные затраты / итоговый годный объём | C11: Общие производственные затраты; итоговый годный объём | D11: =Затраты!D5 -> 14713.037 | E11: долл. США/л | F11: В данной области расчёта численно совпадает с CPU
A12: Себестоимость единицы продукции (CPU) | B12: Общие производственные затраты / итоговый годный объём | C12: Общие производственные затраты; итоговый годный объём | D12: =Затраты!D6 -> 14713.037 | E12: долл. США/л | F12: Себестоимость литра итоговой годной продукции
A13: Массовая ресурсоёмкость | B13: Масса сырья / итоговый годный объём | C13: Raw_Material_Mass_kg (масса сырья) | D13: НЕ РАССЧИТЫВАЕТСЯ | E13: кг/л | F13: Параметр Raw_Material_Mass_kg отсутствует в исходных данных
A14: Штраф TTM по параметрам задания | B14: Мультипликативная потеря сохраняемой стоимости из-за задержки | C14: Параметры TTM в строке 2 | D14: =TTM!G2 -> 0.26285941 | E14: безразмерная величина | F14: Ставка дисконтирования 10 %, ценовая эрозия 15 %, горизонт 3 года
A15: Штраф TTM по параметрам CSV | B15: Мультипликативная потеря сохраняемой стоимости из-за задержки | C15: Параметры TTM в строке 3 | D15: =TTM!G3 -> 0.28034684 | E15: безразмерная величина | F15: Ставки из CSV показаны отдельным сценарием

Sheet Затраты
A1: Метрика | B1: Пояснение формулы | C1: Используемые параметры | D1: Значение | E1: Единица измерения | F1: Комментарий
A2: Затраты на электроэнергию | B2: Потребление электроэнергии × тариф | C2: Потребление электроэнергии; тариф на электроэнергию | D2: ='Исходные данные'!$D$10*'Исходные данные'!$D$11 -> 25300 | E2: долл. США/месяц | F2: Затраты на покупную электроэнергию
A3: Ежемесячная амортизация | B3: CAPEX / экономический срок / 12 | C3: Капитальная стоимость; экономический срок амортизации | D3: ='Исходные данные'!$D$12/'Исходные данные'!$D$13/12 -> 777777.78 | E3: долл. США/месяц | F3: Набор данных за 30 суток принят за один месяц
A4: Общие производственные затраты | B4: Сырьё + энергия + накладные расходы + амортизация | C4: Исходные данные; затраты на электроэнергию; амортизация | D4: ='Исходные данные'!$D$9+D2+'Исходные данные'!$D$14+D3 -> 1188077.8 | E4: долл. США/месяц | F4: Прозрачная структура полной производственной стоимости
A5: Экономическая ресурсоёмкость | B5: Общие производственные затраты / итоговый годный объём | C5: Общие производственные затраты; итоговый годный объём | D5: =D4/'Исходные данные'!$D$8 -> 14713.037 | E5: долл. США/л | F5: Полная экономическая ресурсоёмкость
A6: Себестоимость единицы продукции (CPU) | B6: Общие производственные затраты / итоговый годный объём | C6: Общие производственные затраты; итоговый годный объём | D6: =D4/'Исходные данные'!$D$8 -> 14713.037 | E6: долл. США/л | F6: Себестоимость единицы продукции
A7: Стоимостной показатель сырья | B7: Затраты на сырьё / итоговый годный объём | C7: Затраты на сырьё; итоговый годный объём | D7: ='Исходные данные'!$D$9/'Исходные данные'!$D$8 -> 2972.1362 | E7: долл. США/л | F7: Стоимостной показатель не заменяет массовую ресурсоёмкость

Sheet TTM
A1: Сценарий | B1: Ставка дисконтирования | C1: Ценовая эрозия | D1: Рыночный горизонт, лет | E1: Задержка, лет | F1: Рыночное окно открыто | G1: Штраф TTM | H1: Комментарий
A2: Параметры задания | B2: 0.1 | C2: 0.15 | D2: 3 | E2: 0.5 | F2: 1 | G2: =IF(OR(F2=0,E2>=D2),1,1-(1/(1+B2)^E2)*EXP(-C2*E2)*((D2-E2)/D2)*F2) -> 0.26285941 | H2: Параметры практического задания
A3: Параметры CSV | B3: 0.12 | C3: 0.18 | D3: 3 | E3: 0.5 | F3: 1 | G3: =IF(OR(F3=0,E3>=D3),1,1-(1/(1+B3)^E3)*EXP(-C3*E3)*((D3-E3)/D3)*F3) -> 0.28034684 | H3: Параметры из исходного CSV
A4: Базовый для стресс-теста | B4: 0.1 | C4: 0.15 | D4: 3 | E4: 0 | F4: 1 | G4: =IF(OR(F4=0,E4>=D4),1,1-(1/(1+B4)^E4)*EXP(-C4*E4)*((D4-E4)/D4)*F4) -> 0 | H4: Задержка из базового столбца сравнительного CSV
A5: Стрессовый | B5: 0.1 | C5: 0.15 | D5: 3 | E5: 0.5 | F5: 1 | G5: =IF(OR(F5=0,E5>=D5),1,1-(1/(1+B5)^E5)*EXP(-C5*E5)*((D5-E5)/D5)*F5) -> 0.26285941 | H5: Задержка из стрессового CSV

Sheet Стресс-тест
A1: Метрика | B1: Базовый сценарий | C1: Стрессовый сценарий | D1: Абсолютное изменение | E1: Относительное изменение | F1: Интерпретация
A2: Выход годных с первого прохода (FPY) | B2: ='Исходные данные'!$D$7/'Исходные данные'!$D$6 -> 0.75 | C2: ='Исходные данные'!$D$25/'Исходные данные'!$D$24 -> 0.4 | D2: =C2-B2 -> -0.35 | E2: =IF(B2=0,NA(),D2/ABS(B2)) -> -0.46666667 | F2: Снижается доля годной продукции первого прохода
A3: Общая эффективность оборудования (OEE) | B3: =('Исходные данные'!$D$4/'Исходные данные'!$D$3)*(('Исходные данные'!$D$3/'Исходные данные'!$D$5)*'Исходные данные'!$D$6/'Исходные данные'!$D$4)*('Исходные данные'!$D$7/'Исходные данные'!$D$6) -> 0.59375 | C3: =('Исходные данные'!$D$22/'Исходные данные'!$D$21)*(('Исходные данные'!$D$21/'Исходные данные'!$D$23)*'Исходные данные'!$D$24/'Исходные данные'!$D$22)*('Исходные данные'!$D$25/'Исходные данные'!$D$24) -> 0.31666667 | D3: =C3-B3 -> -0.27708333 | E3: =IF(B3=0,NA(),D3/ABS(B3)) -> -0.46666667 | F3: Снижение качества уменьшает общую эффективность оборудования
A4: Полная эффективная производительность оборудования (TEEP) | B4: =B3*('Исходные данные'!$D$3/'Исходные данные'!$D$2) -> 0.39583333 | C4: =C3*('Исходные данные'!$D$21/'Исходные данные'!$D$20) -> 0.21111111 | D4: =C4-B4 -> -0.18472222 | E4: =IF(B4=0,NA(),D4/ABS(B4)) -> -0.46666667 | F4: Использование календарного времени не изменяется
A5: Затраты на электроэнергию | B5: ='Исходные данные'!$D$10*'Исходные данные'!$D$11 -> 25300 | C5: ='Исходные данные'!$D$28*'Исходные данные'!$D$29 -> 75900 | D5: =C5-B5 -> 50600 | E5: =IF(B5=0,NA(),D5/ABS(B5)) -> 2 | F5: Трёхкратный тариф увеличивает затраты на электроэнергию
A6: Экономическая ресурсоёмкость | B6: =('Исходные данные'!$D$9+'Исходные данные'!$D$10*'Исходные данные'!$D$11+'Исходные данные'!$D$14+'Исходные данные'!$D$12/'Исходные данные'!$D$13/12)/'Исходные данные'!$D$8 -> 14713.037 | C6: =('Исходные данные'!$D$27+'Исходные данные'!$D$28*'Исходные данные'!$D$29+'Исходные данные'!$D$32+'Исходные данные'!$D$30/'Исходные данные'!$D$31/12)/'Исходные данные'!$D$26 -> 15339.663 | D6: =C6-B6 -> 626.62539 | E6: =IF(B6=0,NA(),D6/ABS(B6)) -> 0.042589804 | F6: Рост затрат повышает стоимость ресурсов на литр годной продукции
A7: Себестоимость единицы продукции (CPU) | B7: =B6 -> 14713.037 | C7: =C6 -> 15339.663 | D7: =C7-B7 -> 626.62539 | E7: =IF(B7=0,NA(),D7/ABS(B7)) -> 0.042589804 | F7: Численно совпадает с экономической ресурсоёмкостью в текущей области расчёта
A8: Штраф за задержку вывода на рынок (TTM) | B8: =TTM!G4 -> 0 | C8: =TTM!G5 -> 0.26285941 | D8: =C8-B8 -> 0.26285941 | E8: =IF(B8=0,NA(),D8/ABS(B8)) -> #N/A | F8: Задержка создаёт мультипликативный экономический штраф

Sheet Сверка Excel–Python
A1: Метрика | B1: Значение Excel | C1: Значение Python | D1: Абсолютное отклонение | E1: Относительное отклонение | F1: Допуск | G1: Статус | H1: Вероятная причина | I1: Временная метка
A2: Доступность оборудования | B2: 0.8125 | C2: 0.8125 | D2: 0 | E2: 0 | F2: 1e-09 | G2: СОВПАДАЕТ | I2: 2026-09-17T10:28:02.400846+00:00
A3: Себестоимость единицы продукции (CPU) | B3: 14713.037 | C3: 14713.037 | D3: 0 | E3: 0 | F3: 1e-09 | G3: СОВПАДАЕТ | I3: 2026-09-17T10:28:02.400846+00:00
A4: Экономическая ресурсоёмкость | B4: 14713.037 | C4: 14713.037 | D4: 0 | E4: 0 | F4: 1e-09 | G4: СОВПАДАЕТ | I4: 2026-09-17T10:28:02.400846+00:00
A5: Затраты на электроэнергию | B5: 25300 | C5: 25300 | D5: 0 | E5: 0 | F5: 1e-09 | G5: СОВПАДАЕТ | I5: 2026-09-17T10:28:02.400846+00:00
A6: Энергетическая ресурсоёмкость | B6: 1424.1486 | C6: 1424.1486 | D6: 0 | E6: 0 | F6: 1e-09 | G6: СОВПАДАЕТ | I6: 2026-09-17T10:28:02.400846+00:00
A7: Выход годных с первого прохода (FPY) | B7: 0.75 | C7: 0.75 | D7: 0 | E7: 0 | F7: 1e-09 | G7: СОВПАДАЕТ | I7: 2026-09-17T10:28:02.400846+00:00
A8: Итоговый выход годных | B8: 0.85 | C8: 0.85 | D8: 0 | E8: 0 | F8: 1e-09 | G8: СОВПАДАЕТ | I8: 2026-09-17T10:28:02.400846+00:00
A9: Массовая ресурсоёмкость | F9: 1e-09 | G9: НЕ РАССЧИТЫВАЕТСЯ | H9: Значение Excel недоступно | I9: 2026-09-17T10:28:02.400846+00:00
A10: Ежемесячная амортизация | B10: 777777.78 | C10: 777777.78 | D10: 0 | E10: 0 | F10: 1e-09 | G10: СОВПАДАЕТ | I10: 2026-09-17T10:28:02.400846+00:00
A11: Общая эффективность оборудования (OEE) | B11: 0.59375 | C11: 0.59375 | D11: 0 | E11: 0 | F11: 1e-09 | G11: СОВПАДАЕТ | I11: 2026-09-17T10:28:02.400846+00:00
A12: Производительность оборудования | B12: 0.97435897 | C12: 0.97435897 | D12: 0 | E12: 0 | F12: 1e-09 | G12: СОВПАДАЕТ | I12: 2026-09-17T10:28:02.400846+00:00
A13: Коэффициент качества | B13: 0.75 | C13: 0.75 | D13: 0 | E13: 0 | F13: 1e-09 | G13: СОВПАДАЕТ | I13: 2026-09-17T10:28:02.400846+00:00
A14: Стоимостной показатель сырья | B14: 2972.1362 | C14: 2972.1362 | D14: 0 | E14: 0 | F14: 1e-09 | G14: СОВПАДАЕТ | I14: 2026-09-17T10:28:02.400846+00:00
A15: Полная эффективная производительность оборудования (TEEP) | B15: 0.39583333 | C15: 0.39583333 | D15: 0 | E15: 0 | F15: 1e-09 | G15: СОВПАДАЕТ | I15: 2026-09-17T10:28:02.400846+00:00
A16: Штраф TTM по параметрам задания | B16: 0.26285941 | C16: 0.26285941 | D16: 0 | E16: 0 | F16: 1e-09 | G16: СОВПАДАЕТ | I16: 2026-09-17T10:28:02.400846+00:00
A17: Штраф TTM по параметрам CSV | B17: 0.28034684 | C17: 0.28034684 | D17: 0 | E17: 0 | F17: 1e-09 | G17: СОВПАДАЕТ | I17: 2026-09-17T10:28:02.400846+00:00
A18: Общие производственные затраты | B18: 1188077.8 | C18: 1188077.8 | D18: 0 | E18: 0 | F18: 1e-09 | G18: СОВПАДАЕТ | I18: 2026-09-17T10:28:02.400846+00:00
A19: Использование календарного времени | B19: 0.66666667 | C19: 0.66666667 | D19: 0 | E19: 0 | F19: 1e-09 | G19: СОВПАДАЕТ | I19: 2026-09-17T10:28:02.400846+00:00

Sheet Harness Log
A1: № | B1: Этап | C1: Запрос к ИИ / задача | D1: Сгенерированный или изменённый фрагмент кода | E1: Обнаруженная ошибка / галлюцинация | F1: Причина | G1: Как исправлено | H1: Результат повторной проверки
A2: 1 | B2: Аудит показателей качества | C2: Развести FPY и итоговый выход годных | D2: fpy = first_pass_good_units / actual_output; final_yield = final_good_units / actual_output | E2: FPY и Final Yield могли быть ошибочно приняты за один показатель | F2: Итоговый годный объём включает продукцию после переделки | G2: Показатели реализованы и раскрыты раздельно | H2: Тест подтверждает FPY 75 %, Final Yield 85 %
A3: 2 | B3: Аудит параметров TTM | C3: Сопоставить параметры задания и CSV | D3: assignment_ttm = ttm.calculate(delay, 0.10, 0.15, 3.0, window) | E3: В задании r=10 %, α=15 %, а в CSV r=12 %, α=18 % | F3: Исходные материалы задают разные сценарии | G3: Оба сценария рассчитаны и раскрыты отдельно | H3: Получены штрафы 26,285941 % и 28,034684 % без подмены параметров
A4: 3 | B4: Стресс-сценарий TTM | C4: Выбрать корректную базовую задержку | D4: baseline_stress_ttm = ttm.calculate(comparison.delay[0], 0.10, 0.15, 3.0, window) | E4: Pilot CSV содержит задержку 0,5 года, comparison baseline — 0 лет | F4: Pilot и сравнительный baseline имеют разное назначение | G4: Для стресс-сравнения использован baseline comparison CSV | H4: Тест подтверждает изменение штрафа TTM с 0 % до 26,285941 %
A5: 4 | B5: Аудит ресурсоёмкости | C5: Проверить вычислимость массовой ресурсоёмкости | D5: mass_intensity = NOT_COMPUTABLE | E5: Масса сырья отсутствует, а стоимость не может заменить массу | F5: В CSV нет Raw_Material_Mass_kg | G5: Метрика помечена НЕ РАССЧИТЫВАЕТСЯ, стоимостной proxy показан отдельно | H5: Excel и Python одинаково фиксируют одно невычислимое значение
A6: 5 | B6: Пересчёт Excel | C6: Получить кэшированные результаты формул | D6: excel.CalculateFullRebuild(); workbook.Save() | E6: openpyxl сохраняет формулы, но не вычисляет их | F6: Библиотека не является движком Excel | G6: Добавлен реальный пересчёт установленным Microsoft Excel | H6: Из кэша прочитаны FPY 0,75, OEE 0,59375 и CPU 14 713,0374957
A7: 6 | B7: Жизненный цикл COM | C7: Исключить сбой освобождения Excel COM | D7: subprocess.run([sys.executable, excel_worker.py, workbook_path]) | E7: Первый интеграционный подход мог завершаться RPC_E_DISCONNECTED | F7: COM-прокси переживали закрытие Excel в долгоживущем процессе | G7: Пересчёт изолирован в короткоживущем worker-процессе | H7: Интеграционный тест завершается без RPC fault и с корректным кэшем
A8: 7 | B8: Архитектура контрольных журналов | C8: Развести журнал реализации и числовую сверку | D8: implementation_log_entries и reconciliation_rows | E8: Числовая сверка была ошибочно названа Harness Log | F8: Два разных типа доказательств использовали одно название | G8: Числовая проверка переименована в «Сверка Excel–Python», Harness Log выделен отдельно | H8: Отчёты содержат два самостоятельных раздела и восемь обязательных артефактов

Sheet Структура OPEX
A1: Категория затрат | B1: Доля
A2: Сырье и прекурсоры | B2: 0.25
A3: Утилиты | B3: 0.2
A4: Персонал | B4: 0.3
A5: ТОиР | B5: 0.15
A6: Комплаенс, качество и метрология | B6: 0.1

Sheet Допущения
A1: Код | B1: Допущение | C1: Обоснование | D1: Влияние | E1: Источник | F1: Статус
A2: A01 | B2: Расчётный период — один месяц | C2: Calendar_Hours = 720 = 30 × 24 | D2: Месячная амортизация | E2: CSV | F2: Принято
A3: A02 | B3: Нормативное время цикла = плановое время / плановый выпуск | C3: Отдельное поле отсутствует | D3: Производительность и OEE | E3: Лекция + CSV | F3: Принято
A4: A03 | B4: Знаменатель CPU — итоговый годный объём | C4: Это объём после итогового контроля | D4: CPU и ресурсоёмкость | E4: Лекция + задание | F4: Принято

Sheet Проблемы данных
A1: Проблема | B1: Параметр | C1: Критичность | D1: Влияние | E1: Рекомендуемое действие
A2: Отсутствует масса сырья | B2: Raw_Material_Mass_kg | C2: ВЫСОКАЯ | D2: Массовая ресурсоёмкость не рассчитывается | E2: Добавить массу потреблённого сырья в килограммах
A3: Параметры TTM расходятся | B3: Discount_Rate; Price_Erosion_Rate | C3: СРЕДНЯЯ | D3: Получаются разные штрафы TTM | E3: Показывать сценарии задания и CSV отдельно
A4: Задержка пилотного сценария отличается от базового comparison CSV | B4: Delay_Years | C4: СРЕДНЯЯ | D4: Пилотный сценарий не является сценарием без задержки | E4: Использовать comparison CSV для проверки стресс-сценария
